[
  {
    "id": 1,
    "taskName": "Try a new coffee shop",
    "date": "1713640925000",
    "done": false,
    "important": true,
    "location": "palace"
  },
  {
    "id": 2,
    "taskName": "Have a paint night",
    "date": "1713609870000",
    "done": false,
    "important": false,
    "location": "factory"
  },
  {
    "id": 3,
    "taskName": "Do a DIY project",
    "date": "1713701336000",
    "done": false,
    "important": true,
    "location": "palace"
  },
  {
    "id": 4,
    "taskName": "Try a new tea flavor",
    "date": "1713490658000",
    "done": false,
    "important": true,
    "location": "shrine"
  },
  {
    "id": 5,
    "taskName": "Try a new type of cuisine",
    "date": "1713726055000",
    "done": false,
    "important": true,
    "location": "pagoda"
  },
  {
    "id": 6,
    "taskName": "Cook a new recipe",
    "date": "1713470765000",
    "done": false,
    "important": true,
    "location": "cinema"
  },
  {
    "id": 7,
    "taskName": "Have a bonfire",
    "date": "1713397807000",
    "done": false,
    "important": true,
    "location": "zoo"
  },
  {
    "id": 8,
    "taskName": "Try a new ice cream flavor",
    "date": "1713465016000",
    "done": false,
    "important": true,
    "location": "castle"
  },
  {
    "id": 9,
    "taskName": "Water the plants",
    "date": "1713520974000",
    "done": false,
    "important": false,
    "location": "igloo"
  },
  {
    "id": 10,
    "taskName": "Visit a castle",
    "date": "1713399484000",
    "done": false,
    "important": false,
    "location": "treehouse"
  },
  {
    "id": 11,
    "taskName": "Have a game night",
    "date": "1713560366000",
    "done": false,
    "important": true,
    "location": "apartment"
  },
  {
    "id": 12,
    "taskName": "Take out the trash",
    "date": "1713586659000",
    "done": false,
    "important": false,
    "location": "volcano"
  },
  {
    "id": 13,
    "taskName": "Visit a castle",
    "date": "1713367421000",
    "done": false,
    "important": true,
    "location": "condo"
  },
  {
    "id": 14,
    "taskName": "Take out the trash",
    "date": "1713611913000",
    "done": false,
    "important": false,
    "location": "lake"
  },
  {
    "id": 15,
    "taskName": "Water the plants",
    "date": "1713478850000",
    "done": false,
    "important": false,
    "location": "shrine"
  },
  {
    "id": 16,
    "taskName": "Go to a jazz club",
    "date": "1713675944000",
    "done": false,
    "important": true,
    "location": "skyscraper"
  },
  {
    "id": 17,
    "taskName": "Take a nap",
    "date": "1713703942000",
    "done": false,
    "important": true,
    "location": "ocean"
  },
  {
    "id": 18,
    "taskName": "Have a potluck dinner",
    "date": "1713636476000",
    "done": false,
    "important": true,
    "location": "school"
  },
  {
    "id": 19,
    "taskName": "Take a nap",
    "date": "1713482058000",
    "done": false,
    "important": true,
    "location": "motorhome"
  },
  {
    "id": 20,
    "taskName": "Attend a yoga class",
    "date": "1713345599000",
    "done": false,
    "important": true,
    "location": "tent"
  },
  {
    "id": 21,
    "taskName": "Plan a weekend getaway",
    "date": "1713492050000",
    "done": false,
    "important": true,
    "location": "library"
  },
  {
    "id": 22,
    "taskName": "Read a book",
    "date": "1713607732000",
    "done": false,
    "important": true,
    "location": "train station"
  },
  {
    "id": 23,
    "taskName": "Watch a movie",
    "date": "1713476121000",
    "done": false,
    "important": true,
    "location": "suburb"
  },
  {
    "id": 24,
    "taskName": "Have a picnic",
    "date": "1713612329000",
    "done": false,
    "important": true,
    "location": "houseboat"
  },
  {
    "id": 25,
    "taskName": "Have a potluck dinner",
    "date": "1713410684000",
    "done": false,
    "important": true,
    "location": "beach"
  },
  {
    "id": 26,
    "taskName": "Go for a bike ride",
    "date": "1713367441000",
    "done": false,
    "important": false,
    "location": "houseboat"
  },
  {
    "id": 27,
    "taskName": "Take a dance class",
    "date": "1713688094000",
    "done": false,
    "important": false,
    "location": "restaurant"
  },
  {
    "id": 28,
    "taskName": "Go for a bike ride",
    "date": "1713562573000",
    "done": false,
    "important": false,
    "location": "palace"
  },
  {
    "id": 29,
    "taskName": "Go to a pottery class",
    "date": "1713427168000",
    "done": false,
    "important": true,
    "location": "yurt"
  },
  {
    "id": 30,
    "taskName": "Try a new breakfast recipe",
    "date": "1713594168000",
    "done": false,
    "important": false,
    "location": "yurt"
  },
  {
    "id": 31,
    "taskName": "Try a new hobby",
    "date": "1713566344000",
    "done": false,
    "important": true,
    "location": "ocean"
  },
  {
    "id": 32,
    "taskName": "Water the plants",
    "date": "1713349277000",
    "done": false,
    "important": true,
    "location": "mansion"
  },
  {
    "id": 33,
    "taskName": "Go to a poetry reading",
    "date": "1713439274000",
    "done": false,
    "important": true,
    "location": "bus stop"
  },
  {
    "id": 34,
    "taskName": "Try a new ice cream flavor",
    "date": "1713534106000",
    "done": false,
    "important": false,
    "location": "igloo"
  },
  {
    "id": 35,
    "taskName": "Visit a castle",
    "date": "1713698120000",
    "done": false,
    "important": false,
    "location": "igloo"
  },
  {
    "id": 36,
    "taskName": "Cook a new recipe",
    "date": "1713544284000",
    "done": false,
    "important": false,
    "location": "restaurant"
  },
  {
    "id": 37,
    "taskName": "Attend a virtual event",
    "date": "1713717356000",
    "done": false,
    "important": false,
    "location": "treehouse"
  },
  {
    "id": 38,
    "taskName": "Go for a walk",
    "date": "1713700965000",
    "done": false,
    "important": false,
    "location": "mansion"
  },
  {
    "id": 39,
    "taskName": "Clean the bathroom",
    "date": "1713529001000",
    "done": false,
    "important": false,
    "location": "mansion"
  },
  {
    "id": 40,
    "taskName": "Take a bubble bath",
    "date": "1713668794000",
    "done": false,
    "important": false,
    "location": "tent"
  },
  {
    "id": 41,
    "taskName": "Visit a zoo",
    "date": "1713423564000",
    "done": false,
    "important": false,
    "location": "restaurant"
  },
  {
    "id": 42,
    "taskName": "Try a new hairstyle",
    "date": "1713532040000",
    "done": false,
    "important": true,
    "location": "mountain"
  },
  {
    "id": 43,
    "taskName": "Visit a wildlife sanctuary",
    "date": "1713743958000",
    "done": false,
    "important": false,
    "location": "ocean"
  },
  {
    "id": 44,
    "taskName": "Go to a poetry reading",
    "date": "1713553294000",
    "done": false,
    "important": false,
    "location": "garden"
  },
  {
    "id": 45,
    "taskName": "Go to a concert",
    "date": "1713717466000",
    "done": false,
    "important": false,
    "location": "ocean"
  },
  {
    "id": 46,
    "taskName": "Go to a carnival",
    "date": "1713611046000",
    "done": false,
    "important": false,
    "location": "houseboat"
  },
  {
    "id": 47,
    "taskName": "Visit a botanical park",
    "date": "1713669765000",
    "done": false,
    "important": false,
    "location": "houseboat"
  },
  {
    "id": 48,
    "taskName": "Visit a botanical park",
    "date": "1713403607000",
    "done": false,
    "important": true,
    "location": "lighthouse"
  },
  {
    "id": 49,
    "taskName": "Visit a lighthouse",
    "date": "1713319259000",
    "done": false,
    "important": true,
    "location": "cafe"
  },
  {
    "id": 50,
    "taskName": "Do the laundry",
    "date": "1713368975000",
    "done": false,
    "important": true,
    "location": "factory"
  },
  {
    "id": 51,
    "taskName": "Visit a botanical park",
    "date": "1713330520000",
    "done": false,
    "important": true,
    "location": "mansion"
  },
  {
    "id": 52,
    "taskName": "Go stargazing",
    "date": "1713406483000",
    "done": false,
    "important": false,
    "location": "igloo"
  },
  {
    "id": 53,
    "taskName": "Go to a wine tasting",
    "date": "1713730580000",
    "done": false,
    "important": true,
    "location": "zoo"
  },
  {
    "id": 54,
    "taskName": "Have a game night",
    "date": "1713463839000",
    "done": false,
    "important": true,
    "location": "field"
  },
  {
    "id": 55,
    "taskName": "Try a new hairstyle",
    "date": "1713511344000",
    "done": false,
    "important": true,
    "location": "condo"
  },
  {
    "id": 56,
    "taskName": "Have a potluck dinner",
    "date": "1713421691000",
    "done": false,
    "important": false,
    "location": "cafe"
  },
  {
    "id": 57,
    "taskName": "Try a new workout routine",
    "date": "1713604038000",
    "done": false,
    "important": false,
    "location": "jungle"
  },
  {
    "id": 58,
    "taskName": "Try a new workout routine",
    "date": "1713544046000",
    "done": false,
    "important": true,
    "location": "shopping mall"
  },
  {
    "id": 59,
    "taskName": "Try a new hobby",
    "date": "1713413344000",
    "done": false,
    "important": false,
    "location": "condo"
  },
  {
    "id": 60,
    "taskName": "Visit a castle",
    "date": "1713338311000",
    "done": false,
    "important": true,
    "location": "caravan"
  },
  {
    "id": 61,
    "taskName": "Visit a museum",
    "date": "1713632062000",
    "done": false,
    "important": true,
    "location": "caravan"
  },
  {
    "id": 62,
    "taskName": "Write a letter to a loved one",
    "date": "1713595302000",
    "done": false,
    "important": false,
    "location": "motorhome"
  },
  {
    "id": 63,
    "taskName": "Take a dance class",
    "date": "1713683710000",
    "done": false,
    "important": false,
    "location": "mansion"
  },
  {
    "id": 64,
    "taskName": "Try a new ice cream flavor",
    "date": "1713631622000",
    "done": false,
    "important": false,
    "location": "countryside"
  },
  {
    "id": 65,
    "taskName": "Have a barbecue",
    "date": "1713533883000",
    "done": false,
    "important": true,
    "location": "treehouse"
  },
  {
    "id": 66,
    "taskName": "Go to a comedy show",
    "date": "1713670794000",
    "done": false,
    "important": true,
    "location": "palace"
  },
  {
    "id": 67,
    "taskName": "Plan a weekend getaway",
    "date": "1713381445000",
    "done": false,
    "important": false,
    "location": "castle"
  },
  {
    "id": 68,
    "taskName": "Call a friend",
    "date": "1713387184000",
    "done": false,
    "important": true,
    "location": "beach"
  },
  {
    "id": 69,
    "taskName": "Plant a garden",
    "date": "1713446847000",
    "done": false,
    "important": false,
    "location": "castle"
  },
  {
    "id": 70,
    "taskName": "Try a new ice cream flavor",
    "date": "1713558140000",
    "done": false,
    "important": false,
    "location": "bus stop"
  },
  {
    "id": 71,
    "taskName": "Try a new tea flavor",
    "date": "1713518462000",
    "done": false,
    "important": false,
    "location": "apartment"
  },
  {
    "id": 72,
    "taskName": "Bake cookies",
    "date": "1713504697000",
    "done": false,
    "important": false,
    "location": "amusement park"
  },
  {
    "id": 73,
    "taskName": "Visit a botanical garden",
    "date": "1713461558000",
    "done": false,
    "important": true,
    "location": "alley"
  },
  {
    "id": 74,
    "taskName": "Have a picnic",
    "date": "1713316858000",
    "done": false,
    "important": true,
    "location": "library"
  },
  {
    "id": 75,
    "taskName": "Attend a yoga class",
    "date": "1713314977000",
    "done": false,
    "important": false,
    "location": "tent"
  },
  {
    "id": 76,
    "taskName": "Visit a waterfall",
    "date": "1713327985000",
    "done": false,
    "important": false,
    "location": "treehouse"
  },
  {
    "id": 77,
    "taskName": "Visit a wildlife sanctuary",
    "date": "1713649985000",
    "done": false,
    "important": true,
    "location": "igloo"
  },
  {
    "id": 78,
    "taskName": "Try a new dessert recipe",
    "date": "1713585053000",
    "done": false,
    "important": true,
    "location": "castle"
  },
  {
    "id": 79,
    "taskName": "Try a new salad recipe",
    "date": "1713546781000",
    "done": false,
    "important": true,
    "location": "synagogue"
  },
  {
    "id": 80,
    "taskName": "Visit a butterfly garden",
    "date": "1713455852000",
    "done": false,
    "important": true,
    "location": "graveyard"
  },
  {
    "id": 81,
    "taskName": "Try a new dessert recipe",
    "date": "1713578822000",
    "done": false,
    "important": false,
    "location": "gym"
  },
  {
    "id": 82,
    "taskName": "Try a new type of cuisine",
    "date": "1713673344000",
    "done": false,
    "important": true,
    "location": "restaurant"
  },
  {
    "id": 83,
    "taskName": "Have a picnic by the lake",
    "date": "1713674106000",
    "done": false,
    "important": false,
    "location": "ocean"
  },
  {
    "id": 84,
    "taskName": "Go for a walk",
    "date": "1713570329000",
    "done": false,
    "important": true,
    "location": "shopping mall"
  },
  {
    "id": 85,
    "taskName": "Take a scenic drive",
    "date": "1713468854000",
    "done": false,
    "important": false,
    "location": "mosque"
  },
  {
    "id": 86,
    "taskName": "Try a new cocktail recipe",
    "date": "1713422735000",
    "done": false,
    "important": true,
    "location": "castle"
  },
  {
    "id": 87,
    "taskName": "Take a bubble bath",
    "date": "1713402150000",
    "done": false,
    "important": false,
    "location": "restaurant"
  },
  {
    "id": 88,
    "taskName": "Try a new cocktail recipe",
    "date": "1713366042000",
    "done": false,
    "important": true,
    "location": "hospital"
  },
  {
    "id": 89,
    "taskName": "Visit a botanical park",
    "date": "1713657522000",
    "done": false,
    "important": true,
    "location": "castle"
  },
  {
    "id": 90,
    "taskName": "Visit a museum",
    "date": "1713615316000",
    "done": false,
    "important": true,
    "location": "igloo"
  },
  {
    "id": 91,
    "taskName": "Go stargazing",
    "date": "1713338385000",
    "done": false,
    "important": true,
    "location": "cabin"
  },
  {
    "id": 92,
    "taskName": "Try a new salad recipe",
    "date": "1713583999000",
    "done": false,
    "important": false,
    "location": "campsite"
  },
  {
    "id": 93,
    "taskName": "Write a letter to a loved one",
    "date": "1713663367000",
    "done": false,
    "important": false,
    "location": "lighthouse"
  },
  {
    "id": 94,
    "taskName": "Have a picnic in the park",
    "date": "1713332485000",
    "done": false,
    "important": true,
    "location": "tent"
  },
  {
    "id": 95,
    "taskName": "Have a picnic by the lake",
    "date": "1713490704000",
    "done": false,
    "important": false,
    "location": "tent"
  },
  {
    "id": 96,
    "taskName": "Meditate for 10 minutes",
    "date": "1713628960000",
    "done": false,
    "important": false,
    "location": "caravan"
  },
  {
    "id": 97,
    "taskName": "Have a game night",
    "date": "1713643697000",
    "done": false,
    "important": false,
    "location": "field"
  },
  {
    "id": 98,
    "taskName": "Volunteer at a local charity",
    "date": "1713378138000",
    "done": false,
    "important": false,
    "location": "cave"
  },
  {
    "id": 99,
    "taskName": "Try a new cocktail recipe",
    "date": "1713369426000",
    "done": false,
    "important": true,
    "location": "cave"
  },
  {
    "id": 100,
    "taskName": "Plant a garden",
    "date": "1713411771000",
    "done": false,
    "important": true,
    "location": "igloo"
  }
]
